README.md
setup.py
Code/PaRaVis.py
Code/__init__.py
zgdvvVisfsdfs.egg-info/PKG-INFO
zgdvvVisfsdfs.egg-info/SOURCES.txt
zgdvvVisfsdfs.egg-info/dependency_links.txt
zgdvvVisfsdfs.egg-info/requires.txt
zgdvvVisfsdfs.egg-info/top_level.txt