Metadata-Version: 2.1
Name: zgdvvVisfsdfs
Version: 0.0.0
Summary: parallel, efficient and ensemble analysis of Rao's Q spectral diversity using remote sensing datasets.
Author: Mohammad Reza Fathi
Author-email: mmadrzfathi@gmail.com
